dantejcoder/__init__.py
dantejcoder/admin.py
dantejcoder/apps.py
dantejcoder/coder.py
dantejcoder/models.py
dantejcoder/tests.py
dantejcoder/views.py
django_dantejcoder-0.1.dist-info/DESCRIPTION.rst
django_dantejcoder-0.1.dist-info/METADATA
django_dantejcoder-0.1.dist-info/RECORD
django_dantejcoder-0.1.dist-info/WHEEL
django_dantejcoder-0.1.dist-info/metadata.json
django_dantejcoder-0.1.dist-info/top_level.txt
