Metadata-Version: 2.0
Name: django-dantejcoder
Version: 0.1
Summary: A simple Django app to covert standard django-models to json
Home-page: https://github.com/DanteOnline/django-dantejcoder
Author: DanteOnline
Author-email: iamdanteonline@gmail.com
License: GNU General Public License v3.0
Keywords: json,django,JsonResponse,encoder
Platform: UNKNOWN
